Custom_Widgets/__init__.py
Custom_Widgets/AnalogGaugeWidget.py
Custom_Widgets/components/json/style.json
Custom_Widgets/components/python/main.py
Custom_Widgets/components/python/ui_interface.py
Custom_Widgets/components/uis/interface.ui
Custom_Widgets/interface.ui
Custom_Widgets/main.py
Custom_Widgets/ProgressIndicator/__init__.py
Custom_Widgets/ProgressIndicator/interface.ui
Custom_Widgets/ProgressIndicator/test.py
Custom_Widgets/ProgressIndicator/ui_interface.py
Custom_Widgets/ProjectMaker.py
Custom_Widgets/Qss/__init__.py
Custom_Widgets/Qss/_styles.scss
Custom_Widgets/Qss/colorsystem.py
Custom_Widgets/Qss/icons/original_svg/activity.svg
Custom_Widgets/Qss/icons/original_svg/airplay.svg
Custom_Widgets/Qss/icons/original_svg/alert-circle.svg
Custom_Widgets/Qss/icons/original_svg/alert-octagon.svg
Custom_Widgets/Qss/icons/original_svg/alert-triangle.svg
Custom_Widgets/Qss/icons/original_svg/align-center.svg
Custom_Widgets/Qss/icons/original_svg/align-justify.svg
Custom_Widgets/Qss/icons/original_svg/align-left.svg
Custom_Widgets/Qss/icons/original_svg/align-right.svg
Custom_Widgets/Qss/icons/original_svg/anchor.svg
Custom_Widgets/Qss/icons/original_svg/aperture.svg
Custom_Widgets/Qss/icons/original_svg/archive.svg
Custom_Widgets/Qss/icons/original_svg/arrow-down-circle.svg
Custom_Widgets/Qss/icons/original_svg/arrow-down-left.svg
Custom_Widgets/Qss/icons/original_svg/arrow-down-right.svg
Custom_Widgets/Qss/icons/original_svg/arrow-down.svg
Custom_Widgets/Qss/icons/original_svg/arrow-left-circle.svg
Custom_Widgets/Qss/icons/original_svg/arrow-left.svg
Custom_Widgets/Qss/icons/original_svg/arrow-right-circle.svg
Custom_Widgets/Qss/icons/original_svg/arrow-right.svg
Custom_Widgets/Qss/icons/original_svg/arrow-up-circle.svg
Custom_Widgets/Qss/icons/original_svg/arrow-up-left.svg
Custom_Widgets/Qss/icons/original_svg/arrow-up-right.svg
Custom_Widgets/Qss/icons/original_svg/arrow-up.svg
Custom_Widgets/Qss/icons/original_svg/arrow_down.svg
QT_Custom_Widgets-0.1.6.dist-info/WHEEL
QT_Custom_Widgets-0.1.6.dist-info/METADATA
QT_Custom_Widgets-0.1.6.dist-info/license_files/LICENSE
QT_Custom_Widgets-0.1.6.dist-info/RECORD
