Metadata-Version: 2.1
Name: QT-Custom-Widgets
Version: 0.1.6
Summary: Custom widgets and widget animations made for Qt applications
License: GNU General Public Licence v3.0
Author-email: RayLemon <raylemon0424@gmail.com>
Requires-Python: >=3.10,<3.11
Requires-Dist: cairosvg>=2.5.2
Requires-Dist: iconify>=0.0.103
Requires-Dist: matplotlib>=3.5.3
Requires-Dist: mock>=4.0.3
Requires-Dist: qtpy>=2.2.0
Requires-Dist: qtsass>=0.3.0
